ast_toolbox/__init__.py
ast_toolbox/algos/__init__.py
ast_toolbox/algos/backward_algorithm.py
ast_toolbox/algos/ga.py
ast_toolbox/algos/gasm.py
ast_toolbox/algos/go_explore.py
ast_toolbox/algos/mcts.py
ast_toolbox/algos/mctsbv.py
ast_toolbox/algos/mctsrs.py
ast_toolbox/envs/__init__.py
ast_toolbox/envs/ast_env.py
ast_toolbox/envs/go_explore_ast_env.py
ast_toolbox/mcts/ASTSim.py
ast_toolbox/mcts/AST_MCTS.py
ast_toolbox/mcts/AdaptiveStressTesting.py
ast_toolbox/mcts/AdaptiveStressTestingBlindValue.py
ast_toolbox/mcts/AdaptiveStressTestingRandomSeed.py
ast_toolbox/mcts/BoundedPriorityQueues.py
ast_toolbox/mcts/MCTSdpw.py
ast_toolbox/mcts/MDP.py
ast_toolbox/mcts/RNGWrapper.py
ast_toolbox/mcts/__init__.py
ast_toolbox/mcts/tree_plot.py
ast_toolbox/optimizers/__init__.py
ast_toolbox/optimizers/direction_constraint_optimizer.py
ast_toolbox/policies/__init__.py
ast_toolbox/policies/go_explore_policy.py
ast_toolbox/rewards/__init__.py
ast_toolbox/rewards/ast_reward.py
ast_toolbox/rewards/example_av_reward.py
ast_toolbox/samplers/__init__.py
ast_toolbox/samplers/ast_vectorized_sampler.py
ast_toolbox/samplers/batch_sampler.py
ast_toolbox/samplers/parallel_sampler.py
ast_toolbox/simulators/__init__.py
ast_toolbox/simulators/ast_simulator.py
ast_toolbox/simulators/example_av_simulator/__init__.py
ast_toolbox/simulators/example_av_simulator/example_av_simulator.py
ast_toolbox/simulators/example_av_simulator/toy_av_simulator.py
ast_toolbox/spaces/__init__.py
ast_toolbox/spaces/ast_spaces.py
ast_toolbox/spaces/example_av_spaces.py
ast_toolbox/utils/__init__.py
ast_toolbox/utils/analysis_utils.py
ast_toolbox/utils/exp_utils.py
ast_toolbox/utils/ga_argparser.py
ast_toolbox/utils/go_explore_utils.py
ast_toolbox/utils/mcts_utils.py
ast_toolbox/utils/np_weight_init.py
ast_toolbox/utils/seeding.py
ast_toolbox/utils/tree_plot.py
ast_toolbox-2020.9.1.7.dist-info/AUTHORS.rst
ast_toolbox-2020.9.1.7.dist-info/LICENSE
ast_toolbox-2020.9.1.7.dist-info/METADATA
ast_toolbox-2020.9.1.7.dist-info/WHEEL
ast_toolbox-2020.9.1.7.dist-info/entry_points.txt
ast_toolbox-2020.9.1.7.dist-info/top_level.txt
ast_toolbox-2020.9.1.7.dist-info/RECORD
