Metadata-Version: 2.1
Name: ast-toolbox
Version: 2020.9.1.7
Summary: A toolbox for worst-case validation of autonomous policies
Home-page: https://github.com/sisl/AdaptiveStressTestingToolbox
Author: Stanford Intelligent Systems Laboratory
Author-email: mkoren@stanford.edu
License: MIT
Project-URL: Documentation, https://AdaptiveStressTestingToolbox.readthedocs.io/
Project-URL: Changelog, https://AdaptiveStressTestingToolbox.readthedocs.io/en/latest/changelog.html
Project-URL: Issue Tracker, https://github.com/sisl/AdaptiveStressTestingToolbox/issues
Platform: UNKNOWN
Classifier: Development Status :: 5 - Production/Stable
Classifier: Intended Audience :: Developers
Classifier: License :: OSI Approved :: MIT License
Classifier: Operating System :: Unix
Classifier: Operating System :: POSIX
Classifier: Operating System :: Microsoft :: Windows
Classifier: Programming Language :: Python
Classifier: Programming Language :: Python :: 2.7
Classifier: Programming Language :: Python :: 3
Classifier: Programming Language :: Python :: 3.5
Classifier: Programming Language :: Python :: 3.6
Classifier: Programming Language :: Python :: 3.7
Classifier: Programming Language :: Python :: 3.8
Classifier: Programming Language :: Python :: Implementation :: CPython
Classifier: Programming Language :: Python :: Implementation :: PyPy
Classifier: Topic :: Utilities
Requires-Python: >=3.6, !=3.7.*, !=3.8.*, !=3.9.*, !=3.10.*
License-File: LICENSE
License-File: AUTHORS.rst
Requires-Dist: garage (==2019.10.1)
Requires-Dist: gym (==0.12.4)
Requires-Dist: python-dateutil
Requires-Dist: dowel
Requires-Dist: joblib
Requires-Dist: cached-property
Requires-Dist: akro
Requires-Dist: glfw
Requires-Dist: pyprind
Requires-Dist: cma
Requires-Dist: fire
Requires-Dist: depq
Requires-Dist: compress-pickle
Requires-Dist: pydot
Provides-Extra: all
Provides-Extra: ge
Requires-Dist: bsddb3 ; extra == 'ge'
